odoo10_addon_web_widget_image_download-10.0.1.0.0-py2.7-nspkg.pth
odoo/addons/web_widget_image_download/README.rst
odoo/addons/web_widget_image_download/__init__.py
odoo/addons/web_widget_image_download/__manifest__.py
odoo/addons/web_widget_image_download/static/description/icon.png
odoo/addons/web_widget_image_download/static/src/css/web_widget_image_download.css
odoo/addons/web_widget_image_download/static/src/js/web_widget_image_download.js
odoo/addons/web_widget_image_download/static/src/xml/web_widget_image_download.xml
odoo/addons/web_widget_image_download/views/assets.xml
odoo10_addon_web_widget_image_download-10.0.1.0.0.dist-info/DESCRIPTION.rst
odoo10_addon_web_widget_image_download-10.0.1.0.0.dist-info/METADATA
odoo10_addon_web_widget_image_download-10.0.1.0.0.dist-info/RECORD
odoo10_addon_web_widget_image_download-10.0.1.0.0.dist-info/WHEEL
odoo10_addon_web_widget_image_download-10.0.1.0.0.dist-info/metadata.json
odoo10_addon_web_widget_image_download-10.0.1.0.0.dist-info/namespace_packages.txt
odoo10_addon_web_widget_image_download-10.0.1.0.0.dist-info/top_level.txt
